Metadata-Version: 2.1
Name: mathiz
Version: 0.3.0
Summary: Mathiz, a complete web framework
Home-page: https://github.com/firlast/mathiz
Author: Jaedson Silva
Author-email: imunknowuser@protonmail.com
License: UNKNOWN
Project-URL: License, https://github.com/firlast/mathiz/blob/master/LICENSE
Keywords: www,web,server,http,framework,wsblib
Platform: UNKNOWN
Classifier: License :: OSI Approved :: BSD License
Classifier: Development Status :: 3 - Alpha
Classifier: Intended Audience :: Developers
Classifier: Natural Language :: English
Classifier: Operating System :: OS Independent
Classifier: Programming Language :: Python :: 3
Classifier: Topic :: Internet :: WWW/HTTP :: HTTP Servers
Classifier: Topic :: Internet :: WWW/HTTP :: WSGI
